parshift/__init__.py
parshift/annotation.py
parshift/oo_parshift.py
parshift/plotting.py
parshift/py.typed
parshift/statistics.py
parshift-1.0.2.dist-info/licenses/LICENSE
parshift-1.0.2.dist-info/METADATA
parshift-1.0.2.dist-info/WHEEL
parshift-1.0.2.dist-info/top_level.txt
parshift-1.0.2.dist-info/RECORD
