Metadata-Version: 2.4
Name: parshift
Version: 1.0.2
Summary: Python package based on Gibson's framework (2003) for turn-taking in group conversation analysis.
Author-email: Bruno Saraiva <bruno.saraiva@ulusofona.pt>, João Pedro Carvalho <joao.matos.carvalho@ulusofona.pt>, Nuno Fachada <nuno.fachada@ulusofona.pt>, Manuel Pita <manuel.pita@ulusofona.pt>
License: MIT
Project-URL: Homepage, https://github.com/bdfsaraiva/parshift
Project-URL: Bug Tracker, https://github.com/bdfsaraiva/parshift/issues
Project-URL: Documentation, https://bdfsaraiva.github.io/parshift/
Keywords: python,conversation-analysis,participation-shifts,turn-taking
Classifier: License :: OSI Approved :: MIT License
Classifier: Operating System :: OS Independent
Classifier: Programming Language :: Python
Classifier: Intended Audience :: Science/Research
Classifier: Topic :: Scientific/Engineering
Requires-Python: >=3.9
License-File: LICENSE
Requires-Dist: pandas
Requires-Dist: matplotlib
Requires-Dist: squarify
Provides-Extra: dev
Requires-Dist: black; extra == "dev"
Requires-Dist: mkdocs-material>=7.1.11; extra == "dev"
Requires-Dist: mkdocstrings[python]>=0.19.0; extra == "dev"
Requires-Dist: mypy>=1.0; extra == "dev"
Requires-Dist: pandas-stubs>=1.5.0; extra == "dev"
Requires-Dist: pytest>=7.2.0; extra == "dev"
Requires-Dist: pytest-mypy>=0.10; extra == "dev"
Requires-Dist: pytest-cov>=4.0.0; extra == "dev"
Dynamic: license-file
